itk_dev_shared_components/__init__.py
itk_dev_shared_components/eflyt/__init__.py
itk_dev_shared_components/eflyt/eflyt_case.py
itk_dev_shared_components/eflyt/eflyt_letter.py
itk_dev_shared_components/eflyt/eflyt_login.py
itk_dev_shared_components/eflyt/eflyt_search.py
itk_dev_shared_components/eflyt/eflyt_util.py
itk_dev_shared_components/getorganized/__init__.py
itk_dev_shared_components/getorganized/go_api.py
itk_dev_shared_components/graph/__init__.py
itk_dev_shared_components/graph/authentication.py
itk_dev_shared_components/graph/common.py
itk_dev_shared_components/graph/file.py
itk_dev_shared_components/graph/mail.py
itk_dev_shared_components/graph/site.py
itk_dev_shared_components/kmd_nova/__init__.py
itk_dev_shared_components/kmd_nova/authentication.py
itk_dev_shared_components/kmd_nova/cpr.py
itk_dev_shared_components/kmd_nova/nova_cases.py
itk_dev_shared_components/kmd_nova/nova_documents.py
itk_dev_shared_components/kmd_nova/nova_notes.py
itk_dev_shared_components/kmd_nova/nova_objects.py
itk_dev_shared_components/kmd_nova/nova_tasks.py
itk_dev_shared_components/kmd_nova/util.py
itk_dev_shared_components/misc/__init__.py
itk_dev_shared_components/misc/address_lookup.py
itk_dev_shared_components/misc/cpr_util.py
itk_dev_shared_components/misc/cvr_lookup.py
itk_dev_shared_components/misc/file_util.py
itk_dev_shared_components/sap/__init__.py
itk_dev_shared_components/sap/fmcacov.py
itk_dev_shared_components/sap/gridview_util.py
itk_dev_shared_components/sap/multi_session.py
itk_dev_shared_components/sap/opret_kundekontakt.py
itk_dev_shared_components/sap/sap_login.py
itk_dev_shared_components/sap/sap_util.py
itk_dev_shared_components/sap/tree_util.py
itk_dev_shared_components/smtp/__init__.py
itk_dev_shared_components/smtp/smtp_util.py
itk_dev_shared_components-2.14.1.dist-info/licenses/LICENSE
itk_dev_shared_components-2.14.1.dist-info/METADATA
itk_dev_shared_components-2.14.1.dist-info/WHEEL
itk_dev_shared_components-2.14.1.dist-info/top_level.txt
itk_dev_shared_components-2.14.1.dist-info/RECORD
