Metadata-Version: 2.4
Name: itk_dev_shared_components
Version: 2.14.1
Summary: Shared components to use in RPA projects
Author-email: ITK Development <itk-rpa@mkb.aarhus.dk>
Project-URL: Homepage, https://github.com/itk-dev-rpa/itk-dev-shared-components
Project-URL: Bug Tracker, https://github.com/itk-dev-rpa/itk-dev-shared-components/issues
Classifier: Programming Language :: Python :: 3
Classifier: License :: OSI Approved :: MIT License
Classifier: Operating System :: Microsoft :: Windows
Requires-Python: >=3.7
License-File: LICENSE
Requires-Dist: pywin32>=306
Requires-Dist: msal==1.*
Requires-Dist: requests==2.*
Requires-Dist: beautifulsoup4==4.*
Requires-Dist: selenium==4.*
Requires-Dist: uiautomation==2.*
Requires-Dist: requests_ntlm==1.*
Provides-Extra: dev
Requires-Dist: python-dotenv; extra == "dev"
Requires-Dist: flake8; extra == "dev"
Requires-Dist: pylint; extra == "dev"
Dynamic: license-file
